metaparams/__init__.py
metaparams/metaparams.py
metaparams/version.py
metaparams-2.0.3.dist-info/DESCRIPTION.rst
metaparams-2.0.3.dist-info/METADATA
metaparams-2.0.3.dist-info/RECORD
metaparams-2.0.3.dist-info/WHEEL
metaparams-2.0.3.dist-info/metadata.json
metaparams-2.0.3.dist-info/top_level.txt
