Metadata-Version: 2.0
Name: metaparams
Version: 2.0.3
Summary: Declarative parameters definition for classes
Home-page: https://github.com/mementum/metaparams
Author: Daniel Rodriguez
Author-email: danjrod@gmail.com
License: GPLv3+
Download-URL: https://github.com/mementum/metaparams/tarball/2.0.3
Keywords: metaclass,development
Platform: UNKNOWN
Classifier: Development Status :: 5 - Production/Stable
Classifier: Intended Audience :: Developers
Classifier: Topic :: Software Development
Classifier: License :: OSI Approved :: GNU General Public License v3 or later (GPLv3+)
Classifier: Programming Language :: Python :: 3
Classifier: Programming Language :: Python :: 3.3
Classifier: Programming Language :: Python :: 3.4
Classifier: Programming Language :: Python :: 3.5
Classifier: Programming Language :: Python :: 3.6
Classifier: Operating System :: OS Independent
Requires-Dist: metaframe
